bizfylabs/__init__.py
bizfylabs/api.py
bizfylabs/config.py
bizfylabs/main.py
bizfylabs/model.py
bizfylabs-0.1.4.dist-info/METADATA
bizfylabs-0.1.4.dist-info/WHEEL
bizfylabs-0.1.4.dist-info/top_level.txt
bizfylabs-0.1.4.dist-info/RECORD
